Workbook

Sheet Assumptions
A1: Lease-to-own solar for Aleppo factories: assumptions
A2: Blue = input you can change. Yellow = key assumption to verify in interviews. Column C is live and follows the scenario chosen in C4.
A4: Scenario (1 = Base, 2 = Bad, 3 = Good) | C4: 1 | D4: =CHOOSE($C$4,"Base","Bad","Good")
A6: Assumption | B6: Unit | C6: Live | D6: Base | E6: Bad | F6: Good | G6: Source / note
A7: System
A8: PV array size | B8: kWp | C8: =CHOOSE($C$4,D8,E8,F8) | D8: 100 | E8: 100 | F8: 100 | G8: Sized for a mid-size workshop; scale linearly
A9: Battery size | B9: kWh | C9: =CHOOSE($C$4,D9,E9,F9) | D9: 100 | E9: 100 | F9: 100 | G9: Covers evening shift tail and cloud cover
A10: PV equipment cost (modules, mounting, inverters, cabling) | B10: $/W | C10: =CHOOSE($C$4,D10,E10,F10) | D10: 0.34 | E10: 0.408 | F10: 0.3 | G10: Validation Pack estimate; replace with delivered-to-Aleppo quote
A11: Installation labour | B11: $/W | C11: =CHOOSE($C$4,D11,E11,F11) | D11: 0.05 | E11: 0.06 | F11: 0.04 | G11: Validation Pack estimate
A12: LFP battery incl. power conversion | B12: $/kWh | C12: =CHOOSE($C$4,D12,E12,F12) | D12: 180 | E12: 216 | F12: 160 | G12: C&I range $180-300 (Validation Pack)
A13: Controls, metering, remote lockout | B13: $/deal | C13: =CHOOSE($C$4,D13,E13,F13) | D13: 6000 | E13: 7000 | F13: 5000 | G13: Remote shut-off is the collections lever
A14: Freight, import, inland transport | B14: % of equipment | C14: =CHOOSE($C$4,D14,E14,F14) | D14: 0.1 | E14: 0.12 | F14: 0.08 | G14: Validation Pack: ~10% via Mersin or Beirut
A15: Security, anti-theft, insurance setup | B15: $/deal | C15: =CHOOSE($C$4,D15,E15,F15) | D15: 4000 | E15: 5000 | F15: 3000 | G15: Allowance
A16: Engineering, legal, credit check | B16: $/deal | C16: =CHOOSE($C$4,D16,E16,F16) | D16: 3000 | E16: 4000 | F16: 2500 | G16: Allowance per deal
A17: Contingency | B17: % of subtotal | C17: =CHOOSE($C$4,D17,E17,F17) | D17: 0.1 | E17: 0.1 | F17: 0.08
A18: Sourcing margin on equipment | B18: % of cost | C18: =CHOOSE($C$4,D18,E18,F18) | D18: 0.08 | E18: 0.05 | F18: 0.1 | G18: Markup charged to the factory on landed cost
A19: Energy and diesel
A20: Specific solar yield | B20: kWh/kWp/yr | C20: =CHOOSE($C$4,D20,E20,F20) | D20: 1650 | E20: 1600 | F20: 1700 | G20: Unverified; check Global Solar Atlas for the site
A21: Share of output that displaces diesel | B21: % | C21: =CHOOSE($C$4,D21,E21,F21) | D21: 0.8 | E21: 0.65 | F21: 0.85 | G21: Unverified; needs the factory's load profile
A22: PV degradation | B22: %/yr | C22: =CHOOSE($C$4,D22,E22,F22) | D22: 0.005 | E22: 0.007 | F22: 0.004 | G22: Industry standard
A23: Diesel price | B23: $/litre | C23: =CHOOSE($C$4,D23,E23,F23) | D23: 1.3 | E23: 1.11 | F23: 1.4 | G23: Enab Baladi, Sept 2026: three grades, ~$1.11-1.30
A24: Generator fuel burn | B24: litres/kWh | C24: =CHOOSE($C$4,D24,E24,F24) | D24: 0.3 | E24: 0.28 | F24: 0.32 | G24: Typical at decent load; small units burn more
A25: Generator O&M avoided | B25: $/kWh | C25: =CHOOSE($C$4,D25,E25,F25) | D25: 0.05 | E25: 0.03 | F25: 0.05 | G25: Validation Pack estimate
A26: Lease terms
A27: Customer deposit | B27: % of price | C27: =CHOOSE($C$4,D27,E27,F27) | D27: 0.25 | E27: 0.25 | F27: 0.3 | G27: Filters weak buyers; Lebanon SoLR& uses no deposit with donor backing
A28: Lease tenor | B28: months | C28: =CHOOSE($C$4,D28,E28,F28) | D28: 36 | E28: 36 | F28: 36 | G28: Ownership transfers at end; SoLR& uses 5-7 yrs, lenders expect 2-3 yr payback
A29: Lease interest rate | B29: % per year | C29: =CHOOSE($C$4,D29,E29,F29) | D29: 0.28 | E29: 0.28 | F29: 0.3 | G29: USD-indexed; set so the factory still saves from month 1
A30: Collection rate on lease payments | B30: % | C30: =CHOOSE($C$4,D30,E30,F30) | D30: 0.95 | E30: 0.85 | F30: 0.98 | G30: Unverified; ecoligo's 2026 default shows this is the killer
A31: Recovery on uncollected balance (repossess and resell) | B31: % of shortfall | C31: =CHOOSE($C$4,D31,E31,F31) | D31: 0.3 | E31: 0.1 | F31: 0.4 | G31: Remote lockout plus resale of panels and battery
A32: Servicing and monitoring cost | B32: $/month | C32: =CHOOSE($C$4,D32,E32,F32) | D32: 150 | E32: 200 | F32: 120 | G32: Local agent, telemetry, collections
A33: O&M visits during lease | B33: $/year | C33: =CHOOSE($C$4,D33,E33,F33) | D33: 1500 | E33: 2000 | F33: 1200 | G33: Financier covers maintenance until transfer
A34: Investor view
A35: Discount rate (Syria risk-adjusted) | B35: % per year | C35: =CHOOSE($C$4,D35,E35,F35) | D35: 0.25 | E35: 0.25 | F35: 0.25 | G35: Hurdle for unlevered capital in a post-conflict market
A36: Pilot capital pool | B36: $ | C36: =CHOOSE($C$4,D36,E36,F36) | D36: 500000 | E36: 500000 | F36: 500000 | G36: Council: loss-tolerant pilot under $500k

Sheet Deal
A1: One lease-to-own deal
A2: ="Scenario: "&Assumptions!$D$4
A4: Capex build-up ($)
A5: PV equipment | B5: =Assumptions!$C$8*1000*Assumptions!$C$10
A6: Installation labour | B6: =Assumptions!$C$8*1000*Assumptions!$C$11
A7: Battery | B7: =Assumptions!$C$9*Assumptions!$C$12
A8: Controls and remote lockout | B8: =Assumptions!$C$13
A9: Freight and import | B9: =(B5+B7+B8)*Assumptions!$C$14
A10: Security and insurance | B10: =Assumptions!$C$15
A11: Engineering, legal, credit check | B11: =Assumptions!$C$16
A12: Subtotal | B12: =SUM(B5:B11)
A13: Contingency | B13: =B12*Assumptions!$C$17
A14: Total landed cost | B14: =B12+B13
A15: Price to factory (cost + sourcing margin) | B15: =B14*(1+Assumptions!$C$18)
A16: Cost per Wp | B16: =B14/(Assumptions!$C$8*1000)
A18: Lease ($)
A19: Deposit paid at signing | B19: =B15*Assumptions!$C$27
A20: Amount financed | B20: =B15-B19
A21: Monthly lease payment | B21: =PMT(Assumptions!$C$29/12,Assumptions!$C$28,-B20)
A22: Total paid by factory over the lease | B22: =B19+B21*Assumptions!$C$28
A24: Factory's side ($/year 1)
A25: Solar output used (kWh/yr) | B25: =Assumptions!$C$8*Assumptions!$C$20*Assumptions!$C$21
A26: Diesel cost avoided per kWh | B26: =Assumptions!$C$23*Assumptions!$C$24+Assumptions!$C$25
A27: Annual diesel spend avoided | B27: =B25*B26
A28: Annual lease payments | B28: =B21*12
A29: Net saving during lease (per year) | B29: =B27-B28
A30: Saving as % of avoided diesel | B30: =IFERROR(B29/B27,0)
A31: Simple payback on full price (years) | B31: =IFERROR(B15/B27,0)
A32: Months for net saving to repay deposit | B32: =IFERROR(B19/(B29/12),0)
A34: Financier's return
A35: Monthly IRR | B35: =IRR(Cashflows!$I$6:$I$42)
A36: Annualised IRR | B36: =(1+B35)^12-1
A37: NPV at discount rate ($) | B37: =Cashflows!$I$6+NPV((1+Assumptions!$C$35)^(1/12)-1,Cashflows!$I$7:$I$42)
A38: Net cash out at signing ($) | B38: =-Cashflows!$I$6
A39: Total net cash back over lease ($) | B39: =SUM(Cashflows!$I$7:$I$42)
A40: Multiple on cash out | B40: =IFERROR(B39/B38,0)
A41: Month cumulative cash turns positive | B41: =IF(COUNTIF(Cashflows!$J$6:$J$42,"<0")>36,"never",COUNTIF(Cashflows!$J$6:$J$42,"<0"))

Sheet Cashflows
A1: Financier monthly cash flows ($)
A2: Month 0 = signing. Collections are scheduled payments times the collection rate, plus a recovery on the shortfall.
A5: Month | B5: Equipment and install | C5: Deposit | D5: Scheduled payment | E5: Collected | F5: Recovery on shortfall | G5: Servicing | H5: O&M | I5: Net cash flow | J5: Cumulative
A6: 0 | B6: =IF(A6=0,-Deal!$B$14,0) | C6: =IF(A6=0,Deal!$B$19,0) | D6: =IF(AND(A6>=1,A6<=Assumptions!$C$28),Deal!$B$21,0) | E6: =D6*Assumptions!$C$30 | F6: =(D6-E6)*Assumptions!$C$31 | G6: =IF(AND(A6>=1,A6<=Assumptions!$C$28),-Assumptions!$C$32,0) | H6: =IF(AND(A6>=1,A6<=Assumptions!$C$28),-Assumptions!$C$33/12,0) | I6: =B6+C6+E6+F6+G6+H6 | J6: =I6
A7: 1 | B7: =IF(A7=0,-Deal!$B$14,0) | C7: =IF(A7=0,Deal!$B$19,0) | D7: =IF(AND(A7>=1,A7<=Assumptions!$C$28),Deal!$B$21,0) | E7: =D7*Assumptions!$C$30 | F7: =(D7-E7)*Assumptions!$C$31 | G7: =IF(AND(A7>=1,A7<=Assumptions!$C$28),-Assumptions!$C$32,0) | H7: =IF(AND(A7>=1,A7<=Assumptions!$C$28),-Assumptions!$C$33/12,0) | I7: =B7+C7+E7+F7+G7+H7 | J7: =J6+I7
A8: 2 | B8: =IF(A8=0,-Deal!$B$14,0) | C8: =IF(A8=0,Deal!$B$19,0) | D8: =IF(AND(A8>=1,A8<=Assumptions!$C$28),Deal!$B$21,0) | E8: =D8*Assumptions!$C$30 | F8: =(D8-E8)*Assumptions!$C$31 | G8: =IF(AND(A8>=1,A8<=Assumptions!$C$28),-Assumptions!$C$32,0) | H8: =IF(AND(A8>=1,A8<=Assumptions!$C$28),-Assumptions!$C$33/12,0) | I8: =B8+C8+E8+F8+G8+H8 | J8: =J7+I8
A9: 3 | B9: =IF(A9=0,-Deal!$B$14,0) | C9: =IF(A9=0,Deal!$B$19,0) | D9: =IF(AND(A9>=1,A9<=Assumptions!$C$28),Deal!$B$21,0) | E9: =D9*Assumptions!$C$30 | F9: =(D9-E9)*Assumptions!$C$31 | G9: =IF(AND(A9>=1,A9<=Assumptions!$C$28),-Assumptions!$C$32,0) | H9: =IF(AND(A9>=1,A9<=Assumptions!$C$28),-Assumptions!$C$33/12,0) | I9: =B9+C9+E9+F9+G9+H9 | J9: =J8+I9
A10: 4 | B10: =IF(A10=0,-Deal!$B$14,0) | C10: =IF(A10=0,Deal!$B$19,0) | D10: =IF(AND(A10>=1,A10<=Assumptions!$C$28),Deal!$B$21,0) | E10: =D10*Assumptions!$C$30 | F10: =(D10-E10)*Assumptions!$C$31 | G10: =IF(AND(A10>=1,A10<=Assumptions!$C$28),-Assumptions!$C$32,0) | H10: =IF(AND(A10>=1,A10<=Assumptions!$C$28),-Assumptions!$C$33/12,0) | I10: =B10+C10+E10+F10+G10+H10 | J10: =J9+I10
A11: 5 | B11: =IF(A11=0,-Deal!$B$14,0) | C11: =IF(A11=0,Deal!$B$19,0) | D11: =IF(AND(A11>=1,A11<=Assumptions!$C$28),Deal!$B$21,0) | E11: =D11*Assumptions!$C$30 | F11: =(D11-E11)*Assumptions!$C$31 | G11: =IF(AND(A11>=1,A11<=Assumptions!$C$28),-Assumptions!$C$32,0) | H11: =IF(AND(A11>=1,A11<=Assumptions!$C$28),-Assumptions!$C$33/12,0) | I11: =B11+C11+E11+F11+G11+H11 | J11: =J10+I11
A12: 6 | B12: =IF(A12=0,-Deal!$B$14,0) | C12: =IF(A12=0,Deal!$B$19,0) | D12: =IF(AND(A12>=1,A12<=Assumptions!$C$28),Deal!$B$21,0) | E12: =D12*Assumptions!$C$30 | F12: =(D12-E12)*Assumptions!$C$31 | G12: =IF(AND(A12>=1,A12<=Assumptions!$C$28),-Assumptions!$C$32,0) | H12: =IF(AND(A12>=1,A12<=Assumptions!$C$28),-Assumptions!$C$33/12,0) | I12: =B12+C12+E12+F12+G12+H12 | J12: =J11+I12
A13: 7 | B13: =IF(A13=0,-Deal!$B$14,0) | C13: =IF(A13=0,Deal!$B$19,0) | D13: =IF(AND(A13>=1,A13<=Assumptions!$C$28),Deal!$B$21,0) | E13: =D13*Assumptions!$C$30 | F13: =(D13-E13)*Assumptions!$C$31 | G13: =IF(AND(A13>=1,A13<=Assumptions!$C$28),-Assumptions!$C$32,0) | H13: =IF(AND(A13>=1,A13<=Assumptions!$C$28),-Assumptions!$C$33/12,0) | I13: =B13+C13+E13+F13+G13+H13 | J13: =J12+I13
A14: 8 | B14: =IF(A14=0,-Deal!$B$14,0) | C14: =IF(A14=0,Deal!$B$19,0) | D14: =IF(AND(A14>=1,A14<=Assumptions!$C$28),Deal!$B$21,0) | E14: =D14*Assumptions!$C$30 | F14: =(D14-E14)*Assumptions!$C$31 | G14: =IF(AND(A14>=1,A14<=Assumptions!$C$28),-Assumptions!$C$32,0) | H14: =IF(AND(A14>=1,A14<=Assumptions!$C$28),-Assumptions!$C$33/12,0) | I14: =B14+C14+E14+F14+G14+H14 | J14: =J13+I14
A15: 9 | B15: =IF(A15=0,-Deal!$B$14,0) | C15: =IF(A15=0,Deal!$B$19,0) | D15: =IF(AND(A15>=1,A15<=Assumptions!$C$28),Deal!$B$21,0) | E15: =D15*Assumptions!$C$30 | F15: =(D15-E15)*Assumptions!$C$31 | G15: =IF(AND(A15>=1,A15<=Assumptions!$C$28),-Assumptions!$C$32,0) | H15: =IF(AND(A15>=1,A15<=Assumptions!$C$28),-Assumptions!$C$33/12,0) | I15: =B15+C15+E15+F15+G15+H15 | J15: =J14+I15
A16: 10 | B16: =IF(A16=0,-Deal!$B$14,0) | C16: =IF(A16=0,Deal!$B$19,0) | D16: =IF(AND(A16>=1,A16<=Assumptions!$C$28),Deal!$B$21,0) | E16: =D16*Assumptions!$C$30 | F16: =(D16-E16)*Assumptions!$C$31 | G16: =IF(AND(A16>=1,A16<=Assumptions!$C$28),-Assumptions!$C$32,0) | H16: =IF(AND(A16>=1,A16<=Assumptions!$C$28),-Assumptions!$C$33/12,0) | I16: =B16+C16+E16+F16+G16+H16 | J16: =J15+I16
A17: 11 | B17: =IF(A17=0,-Deal!$B$14,0) | C17: =IF(A17=0,Deal!$B$19,0) | D17: =IF(AND(A17>=1,A17<=Assumptions!$C$28),Deal!$B$21,0) | E17: =D17*Assumptions!$C$30 | F17: =(D17-E17)*Assumptions!$C$31 | G17: =IF(AND(A17>=1,A17<=Assumptions!$C$28),-Assumptions!$C$32,0) | H17: =IF(AND(A17>=1,A17<=Assumptions!$C$28),-Assumptions!$C$33/12,0) | I17: =B17+C17+E17+F17+G17+H17 | J17: =J16+I17
A18: 12 | B18: =IF(A18=0,-Deal!$B$14,0) | C18: =IF(A18=0,Deal!$B$19,0) | D18: =IF(AND(A18>=1,A18<=Assumptions!$C$28),Deal!$B$21,0) | E18: =D18*Assumptions!$C$30 | F18: =(D18-E18)*Assumptions!$C$31 | G18: =IF(AND(A18>=1,A18<=Assumptions!$C$28),-Assumptions!$C$32,0) | H18: =IF(AND(A18>=1,A18<=Assumptions!$C$28),-Assumptions!$C$33/12,0) | I18: =B18+C18+E18+F18+G18+H18 | J18: =J17+I18
... A42: 36 | B42: =IF(A42=0,-Deal!$B$14,0) | C42: =IF(A42=0,Deal!$B$19,0) | D42: =IF(AND(A42>=1,A42<=Assumptions!$C$28),Deal!$B$21,0) | E42: =D42*Assumptions!$C$30 | F42: =(D42-E42)*Assumptions!$C$31 | G42: =IF(AND(A42>=1,A42<=Assumptions!$C$28),-Assumptions!$C$32,0) | H42: =IF(AND(A42>=1,A42<=Assumptions!$C$28),-Assumptions!$C$33/12,0) | I42: =B42+C42+E42+F42+G42+H42 | J42: =J41+I42
A43: Total | B43: =SUM(B6:B42) | C43: =SUM(C6:C42) | D43: =SUM(D6:D42) | E43: =SUM(E6:E42) | F43: =SUM(F6:F42) | G43: =SUM(G6:G42) | H43: =SUM(H6:H42) | I43: =SUM(I6:I42)
A45: Months beyond 36 are left out: ownership transfers to the factory at the end of the lease.

Sheet Compare
A1: Lease-to-own vs. 15-year power-as-a-service
A2: The PaaS column is copied from the Microgrid YC Validation Pack (Oct 2026) and does not recalculate here.
A4: Metric | B4: Lease-to-own (live) | C4: PaaS, own for 15 yrs (Validation Pack)
A5: Capital out per deal ($) | B5: =Deal!$B$38 | C5: 272250
A6: Years capital is exposed | B6: =Assumptions!$C$28/12 | C6: 15
A7: Unlevered IRR | B7: =Deal!$B$36 | C7: 0.164
A8: Clears the 25% Syria hurdle? | B8: =IF(Deal!$B$36>=Assumptions!$C$35,"Yes","No") | C8: No
A9: Bad-case outcome | B9: Switch C4 on Assumptions to 2 | C9: Never pays back ($0.22 tariff, capex +20%, -15% kWh, 85% collection)
A10: Exposure to grid arrival | B10: Ends at transfer (month 36) | C10: Full: 15-yr contract vs. ~3c/kWh utility solar
A11: Who owns the asset after the term | B11: Factory | C11: Developer
A13: Source for PaaS figures: Microgrid YC Validation Pack, 'Unit economics: one factory site' (250 kWp + 500 kWh, $0.26/kWh tariff).

Sheet Pilot pool
A1: What a $500k pilot pool funds
A2: Assumes every dollar collected is relent the following year. Deals are whole numbers.
A4: Year | B4: Cash available ($) | C4: New deals signed | D4: Cash out ($) | E4: Cash back from all live deals ($) | F4: Live deals
A5: 1 | B5: =Assumptions!$C$36 | C5: =IFERROR(INT(B5/Deal!$B$38),0) | D5: =C5*Deal!$B$38 | E5: =(C5)*SUM(Cashflows!$I$7:$I$42)/3 | F5: =C5
A6: 2 | B6: =B5-D5+E5 | C6: =IFERROR(INT(B6/Deal!$B$38),0) | D6: =C6*Deal!$B$38 | E6: =(C5+C6)*SUM(Cashflows!$I$7:$I$42)/3 | F6: =C5+C6
A7: 3 | B7: =B6-D6+E6 | C7: =IFERROR(INT(B7/Deal!$B$38),0) | D7: =C7*Deal!$B$38 | E7: =(C5+C6+C7)*SUM(Cashflows!$I$7:$I$42)/3 | F7: =C5+C6+C7
A8: 4 | B8: =B7-D7+E7 | C8: =IFERROR(INT(B8/Deal!$B$38),0) | D8: =C8*Deal!$B$38 | E8: =(C6+C7+C8)*SUM(Cashflows!$I$7:$I$42)/3 | F8: =C6+C7+C8
A9: 5 | B9: =B8-D8+E8 | C9: =IFERROR(INT(B9/Deal!$B$38),0) | D9: =C9*Deal!$B$38 | E9: =(C7+C8+C9)*SUM(Cashflows!$I$7:$I$42)/3 | F9: =C7+C8+C9
A11: Simplification: each deal's 36 months of net collections are spread evenly over three years, starting the year it is signed.
A12: Deals signed over 5 years | C12: =SUM(C5:C9)
